{  "_typename" : "TH2F",  "fUniqueID" : 0,  "fBits" : 50332168,  "fName" : "CorrelationMatrixSignal",  "fTitle" : "Correlation Matrix (Signal)",  "fLineColor" : 602,  "fLineStyle" : 1,  "fLineWidth" : 3,  "fFillColor" : 0,  "fFillStyle" : 1001,  "fMarkerColor" : 0,  "fMarkerStyle" : 8,  "fMarkerSize" : 1.500000e+00,  "fNcells" : 64,  "fXaxis" : {    "_typename" : "TAxis",    "fUniqueID" : 0,    "fBits" : 51380224,    "fName" : "xaxis",    "fTitle" : "",    "fNdivisions" : 510,    "fAxisColor" : 1,    "fLabelColor" : 1,    "fLabelFont" : 42,    "fLabelOffset" : 1.100000e-02,    "fLabelSize" : 5.500000e-02,    "fTickLength" : 3.000000e-02,    "fTitleOffset" : 1,    "fTitleSize" : 3.500000e-02,    "fTitleColor" : 1,    "fTitleFont" : 42,    "fNbins" : 6,    "fXmin" : 0,    "fXmax" : 6,    "fXbins" : [],    "fFirst" : 0,    "fLast" : 0,    "fBits2" : 3,    "fTimeDisplay" : false,    "fTimeFormat" : "",    "fLabels" : {      "_typename" : "THashList",      "name" : "THashList",      "arr" : [{        "_typename" : "TObjString",        "fUniqueID" : 1,        "fBits" : 50331648,        "fString" : "var0"      }, {        "_typename" : "TObjString",        "fUniqueID" : 2,        "fBits" : 50331648,        "fString" : "var1"      }, {        "_typename" : "TObjString",        "fUniqueID" : 3,        "fBits" : 50331648,        "fString" : "var2"      }, {        "_typename" : "TObjString",        "fUniqueID" : 4,        "fBits" : 50331648,        "fString" : "var3"      }, {        "_typename" : "TObjString",        "fUniqueID" : 5,        "fBits" : 50331648,        "fString" : "var4"      }, {        "_typename" : "TObjString",        "fUniqueID" : 6,        "fBits" : 50331648,        "fString" : "var5"      }],      "opt" : ["", "", "", "", "", ""]    }  },  "fYaxis" : {    "_typename" : "TAxis",    "fUniqueID" : 0,    "fBits" : 50331648,    "fName" : "yaxis",    "fTitle" : "",    "fNdivisions" : 510,    "fAxisColor" : 1,    "fLabelColor" : 1,    "fLabelFont" : 42,    "fLabelOffset" : 5.000000e-03,    "fLabelSize" : 5.500000e-02,    "fTickLength" : 3.000000e-02,    "fTitleOffset" : 1,    "fTitleSize" : 3.500000e-02,    "fTitleColor" : 1,    "fTitleFont" : 42,    "fNbins" : 6,    "fXmin" : 0,    "fXmax" : 6,    "fXbins" : [],    "fFirst" : 0,    "fLast" : 0,    "fBits2" : 3,    "fTimeDisplay" : false,    "fTimeFormat" : "",    "fLabels" : {      "_typename" : "THashList",      "name" : "THashList",      "arr" : [{        "_typename" : "TObjString",        "fUniqueID" : 1,        "fBits" : 50331648,        "fString" : "var0"      }, {        "_typename" : "TObjString",        "fUniqueID" : 2,        "fBits" : 50331648,        "fString" : "var1"      }, {        "_typename" : "TObjString",        "fUniqueID" : 3,        "fBits" : 50331648,        "fString" : "var2"      }, {        "_typename" : "TObjString",        "fUniqueID" : 4,        "fBits" : 50331648,        "fString" : "var3"      }, {        "_typename" : "TObjString",        "fUniqueID" : 5,        "fBits" : 50331648,        "fString" : "var4"      }, {        "_typename" : "TObjString",        "fUniqueID" : 6,        "fBits" : 50331648,        "fString" : "var5"      }],      "opt" : ["", "", "", "", "", ""]    }  },  "fZaxis" : {    "_typename" : "TAxis",    "fUniqueID" : 0,    "fBits" : 50331648,    "fName" : "zaxis",    "fTitle" : "",    "fNdivisions" : 510,    "fAxisColor" : 1,    "fLabelColor" : 1,    "fLabelFont" : 42,    "fLabelOffset" : 5.000000e-03,    "fLabelSize" : 3.500000e-02,    "fTickLength" : 3.000000e-02,    "fTitleOffset" : 1,    "fTitleSize" : 3.500000e-02,    "fTitleColor" : 1,    "fTitleFont" : 42,    "fNbins" : 1,    "fXmin" : 0,    "fXmax" : 1,    "fXbins" : [],    "fFirst" : 0,    "fLast" : 0,    "fBits2" : 0,    "fTimeDisplay" : false,    "fTimeFormat" : "",    "fLabels" : null  },  "fBarOffset" : 0,  "fBarWidth" : 1000,  "fEntries" : 72,  "fTsumw" : 0,  "fTsumw2" : 0,  "fTsumwx" : 0,  "fTsumwx2" : 0,  "fMaximum" : 100,  "fMinimum" : -100,  "fNormFactor" : 0,  "fContour" : [],  "fSumw2" : [],  "fOption" : "",  "fFunctions" : {    "_typename" : "TList",    "name" : "TList",    "arr" : [],    "opt" : []  },  "fBufferSize" : 0,  "fBuffer" : [],  "fBinStatErrOpt" : 0,  "fScalefactor" : 1,  "fTsumwy" : 0,  "fTsumwy2" : 0,  "fTsumwxy" : 0,  "fArray" : [0, 0, 0, 0, 0, 0, 0, 0, 0, 100, 0, 1, 85, 92, 0, 0, 0, 0, 100, 2, -52, 0, 80, 0, 0, 1, 2, 100, 0, 33, 60, 0, 0, 85, -52, 0, 100, 78, -41, 0, 0, 92, 0, 33, 78, 100, 19, 0, 0, 0, 80, 60, -41, 19, 100, 0, 0, 0, 0, 0, 0, 0, 0, 0]}